kinopoisk/__init__.py
kinopoisk/client.py
kinopoisk/data/__init__.py
kinopoisk/data/age_raiting.py
kinopoisk/data/blooper.py
kinopoisk/data/box_office.py
kinopoisk/data/description.py
kinopoisk/data/fact.py
kinopoisk/data/filters/__init__.py
kinopoisk/data/filters/base_filter.py
kinopoisk/data/filters/country.py
kinopoisk/data/filters/genre.py
kinopoisk/data/id.py
kinopoisk/data/movie/__init__.py
kinopoisk/data/movie/base_movie.py
kinopoisk/data/movie/film.py
kinopoisk/data/movie/tv_series/__init__.py
kinopoisk/data/movie/tv_series/episode.py
kinopoisk/data/movie/tv_series/season.py
kinopoisk/data/movie/tv_series/tv_series.py
kinopoisk/data/name.py
kinopoisk/data/person.py
kinopoisk/data/poster.py
kinopoisk/data/production_status.py
kinopoisk/data/raiting.py
kinopoisk/data/review.py
kinopoisk/data/types.py
kinopoisk/data/url.py
kinopoisk/errors/__init__.py
kinopoisk/errors/invalid_token.py
kinopoisk/errors/too_many_requests.py
kinopoisk/utils/__init__.py
kinopoisk_unofficial_api-0.7.0.dist-info/LICENSE
kinopoisk_unofficial_api-0.7.0.dist-info/WHEEL
kinopoisk_unofficial_api-0.7.0.dist-info/METADATA
kinopoisk_unofficial_api-0.7.0.dist-info/RECORD
