Metadata-Version: 2.1
Name: kinopoisk-unofficial-api
Version: 0.7.0
Summary: Simple wrapper of kinopoiskapiunofficial.tech
Home-page: https://github.com/Nawot/kinopoisk-unofficial-api
Keywords: kinopoisk,api
Author: Nawot
Author-email: Nawot001@gmail.com
Requires-Python: >=3.9,<4.0
Classifier: Programming Language :: Python :: 3
Classifier: Programming Language :: Python :: 3.10
Classifier: Programming Language :: Python :: 3.9
Requires-Dist: aiohttp (>=3.8.1,<4.0.0)
Requires-Dist: fuzzywuzzy (>=0.18.0,<0.19.0)
Requires-Dist: python-Levenshtein (>=0.12.2,<0.13.0)
Project-URL: Bug Tracker, https://github.com/Nawot/kinopoisk-unofficial-api/issues
Project-URL: Repository, https://github.com/Nawot/kinopoisk-unofficial-api
